streamcompiler/__init__.py
streamcompiler/__main__.py
streamcompiler/asset.py
streamcompiler/compiler.py
streamcompiler/future.py
streamcompiler/profile.py
stream_compiler-0.1.0.dist-info/METADATA
stream_compiler-0.1.0.dist-info/WHEEL
stream_compiler-0.1.0.dist-info/entry_points.txt
stream_compiler-0.1.0.dist-info/top_level.txt
stream_compiler-0.1.0.dist-info/RECORD
