Metadata-Version: 2.1
Name: stream-compiler
Version: 0.1.0
Summary: A video editor based on a human writeable script language
Home-page: https://github.com/keis/stream-compiler
Author: David Keijser
Author-email: keijser@gmail.com
License: ISC
Platform: UNKNOWN
Classifier: Development Status :: 4 - Beta
Classifier: Natural Language :: English
Classifier: License :: OSI Approved :: ISC License (ISCL)
Classifier: Programming Language :: Python
Classifier: Programming Language :: Python :: 3
Classifier: Topic :: Multimedia :: Video
Requires-Python: >=3.6
Requires-Dist: py-scfg
Requires-Dist: PyGObject
